{
  "project_info": {
    "project_number": "860181601684",
    "firebase_url": "https://rootnet-intranet.firebaseio.com",
    "project_id": "rootnet-intranet",
    "storage_bucket": "rootnet-intranet.appspot.com"
  },
  "client": [
    {
      "client_info": {
        "mobilesdk_app_id": "1:860181601684:android:3557b037d940dbce",
        "android_client_info": {
          "package_name": "com.rootnetapp.rootnetintranet"
        }
      },
      "oauth_client": [
        {
          "client_id": "860181601684-6cd6mbmo0bkmfc6s73dd7c2av269e2eg.apps.googleusercontent.com",
          "client_type": 3
        }
      ],
      "api_key": [
        {
          "current_key": "AIzaSyDy1CzKMHzWES2mmcRknvYSNjrZmtAroSM"
        }
      ],
      "services": {
        "analytics_service": {
          "status": 1
        },
        "appinvite_service": {
          "status": 1,
          "other_platform_oauth_client": []
        },
        "ads_service": {
          "status": 2
        }
      }
    }
  ],
  "configuration_version": "1"
}